{"_cached_at": "2026-01-18T13:27:06.528436", "data": {"data": {"id": 18841694, "sport_id": 1, "league_id": 8, "season_id": 21646, "stage_id": 77464011, "group_id": null, "aggregate_id": null, "round_id": 307072, "state_id": 5, "venue_id": 214, "name": "West Ham United vs Newcastle United", "starting_at": "2023-10-08 13:00:00", "result_info": "Game ended in draw.", "leg": "1/1", "details": null, "length": 90, "placeholder": false, "has_odds": true, "has_premium_odds": false, "starting_at_timestamp": 1696770000, "participants": [{"id": 1, "sport_id": 1, "country_id": 462, "venue_id": 214, "gender": "male", "name": "West Ham United", "short_code": "WHU", "image_path": "https://cdn.sportmonks.com/images/soccer/teams/1/1.png", "founded": 1895, "type": "domestic", "placeholder": false, "last_played_at": "2026-01-17 15:00:00", "meta": {"location": "home", "winner": false, "position": 7}}, {"id": 20, "sport_id": 1, "country_id": 462, "venue_id": 449, "gender": "male", "name": "Newcastle United", "short_code": "NEW", "image_path": "https://cdn.sportmonks.com/images/soccer/teams/20/20.png", "founded": 1892, "type": "domestic", "placeholder": false, "last_played_at": "2026-01-13 20:00:00", "meta": {"location": "away", "winner": false, "position": 8}}], "scores": [{"id": 13308961, "fixture_id": 18841694, "type_id": 1, "participant_id": 1, "score": {"goals": 1, "participant": "home"}, "description": "1ST_HALF"}, {"id": 13310045, "fixture_id": 18841694, "type_id": 2, "participant_id": 1, "score": {"goals": 2, "participant": "home"}, "description": "2ND_HALF"}, {"id": 13308998, "fixture_id": 18841694, "type_id": 1525, "participant_id": 20, "score": {"goals": 2, "participant": "away"}, "description": "CURRENT"}, {"id": 13308997, "fixture_id": 18841694, "type_id": 1525, "participant_id": 1, "score": {"goals": 2, "participant": "home"}, "description": "CURRENT"}, {"id": 13310046, "fixture_id": 18841694, "type_id": 2, "participant_id": 20, "score": {"goals": 2, "participant": "away"}, "description": "2ND_HALF"}, {"id": 13308962, "fixture_id": 18841694, "type_id": 1, "participant_id": 20, "score": {"goals": 0, "participant": "away"}, "description": "1ST_HALF"}], "statistics": [{"id": 24137215, "fixture_id": 18841694, "type_id": 59, "participant_id": 20, "data": {"value": 3}, "location": "away"}, {"id": 24137212, "fixture_id": 18841694, "type_id": 41, "participant_id": 20, "data": {"value": 6}, "location": "away"}, {"id": 24139800, "fixture_id": 18841694, "type_id": 99, "participant_id": 20, "data": {"value": 5}, "location": "away"}, {"id": 24138174, "fixture_id": 18841694, "type_id": 58, "participant_id": 1, "data": {"value": 0}, "location": "home"}, {"id": 24139645, "fixture_id": 18841694, "type_id": 109, "participant_id": 1, "data": {"value": 6}, "location": "home"}, {"id": 24141189, "fixture_id": 18841694, "type_id": 46, "participant_id": 20, "data": {"value": 91}, "location": "away"}, {"id": 24141194, "fixture_id": 18841694, "type_id": 87, "participant_id": 20, "data": {"value": 0}, "location": "away"}, {"id": 24141180, "fixture_id": 18841694, "type_id": 87, "participant_id": 1, "data": {"value": 1}, "location": "home"}, {"id": 24137208, "fixture_id": 18841694, "type_id": 43, "participant_id": 20, "data": {"value": 97}, "location": "away"}, {"id": 24137203, "fixture_id": 18841694, "type_id": 86, "participant_id": 1, "data": {"value": 3}, "location": "home"}, {"id": 24137211, "fixture_id": 18841694, "type_id": 86, "participant_id": 20, "data": {"value": 3}, "location": "away"}, {"id": 24137196, "fixture_id": 18841694, "type_id": 41, "participant_id": 1, "data": {"value": 2}, "location": "home"}, {"id": 24137198, "fixture_id": 18841694, "type_id": 43, "participant_id": 1, "data": {"value": 85}, "location": "home"}, {"id": 24137202, "fixture_id": 18841694, "type_id": 44, "participant_id": 1, "data": {"value": 32}, "location": "home"}, {"id": 24137209, "fixture_id": 18841694, "type_id": 44, "participant_id": 20, "data": {"value": 40}, "location": "away"}, {"id": 24141175, "fixture_id": 18841694, "type_id": 46, "participant_id": 1, "data": {"value": 90}, "location": "home"}, {"id": 24138181, "fixture_id": 18841694, "type_id": 56, "participant_id": 20, "data": {"value": 18}, "location": "away"}, {"id": 24137200, "fixture_id": 18841694, "type_id": 34, "participant_id": 1, "data": {"value": 4}, "location": "home"}, {"id": 24137214, "fixture_id": 18841694, "type_id": 34, "participant_id": 20, "data": {"value": 2}, "location": "away"}, {"id": 24137205, "fixture_id": 18841694, "type_id": 59, "participant_id": 1, "data": {"value": 2}, "location": "home"}, {"id": 24138482, "fixture_id": 18841694, "type_id": 60, "participant_id": 1, "data": {"value": 15}, "location": "home"}, {"id": 24138499, "fixture_id": 18841694, "type_id": 60, "participant_id": 20, "data": {"value": 19}, "location": "away"}, {"id": 24138176, "fixture_id": 18841694, "type_id": 51, "participant_id": 1, "data": {"value": 2}, "location": "home"}, {"id": 24138180, "fixture_id": 18841694, "type_id": 51, "participant_id": 20, "data": {"value": 1}, "location": "away"}, {"id": 691513324, "fixture_id": 18841694, "type_id": 580, "participant_id": 1, "data": {"value": 1}, "location": "home"}, {"id": 691513325, "fixture_id": 18841694, "type_id": 580, "participant_id": 20, "data": {"value": 3}, "location": "away"}, {"id": 691513326, "fixture_id": 18841694, "type_id": 581, "participant_id": 1, "data": {"value": 0}, "location": "home"}, {"id": 691513327, "fixture_id": 18841694, "type_id": 581, "participant_id": 20, "data": {"value": 1}, "location": "away"}, {"id": 24138177, "fixture_id": 18841694, "type_id": 57, "participant_id": 1, "data": {"value": 1}, "location": "home"}, {"id": 24138182, "fixture_id": 18841694, "type_id": 57, "participant_id": 20, "data": {"value": 1}, "location": "away"}, {"id": 24138485, "fixture_id": 18841694, "type_id": 81, "participant_id": 1, "data": {"value": 229}, "location": "home"}, {"id": 24138495, "fixture_id": 18841694, "type_id": 81, "participant_id": 20, "data": {"value": 520}, "location": "away"}, {"id": 24137206, "fixture_id": 18841694, "type_id": 84, "participant_id": 1, "data": {"value": 3}, "location": "home"}, {"id": 24137217, "fixture_id": 18841694, "type_id": 84, "participant_id": 20, "data": {"value": 3}, "location": "away"}, {"id": 24145883, "fixture_id": 18841694, "type_id": 64, "participant_id": 1, "data": {"value": 0}, "location": "home"}, {"id": 24145885, "fixture_id": 18841694, "type_id": 64, "participant_id": 20, "data": {"value": 1}, "location": "away"}, {"id": 24137204, "fixture_id": 18841694, "type_id": 52, "participant_id": 1, "data": {"value": 2}, "location": "home"}, {"id": 24137213, "fixture_id": 18841694, "type_id": 52, "participant_id": 20, "data": {"value": 2}, "location": "away"}, {"id": 24139709, "fixture_id": 18841694, "type_id": 53, "participant_id": 1, "data": {"value": 9}, "location": "home"}, {"id": 24139714, "fixture_id": 18841694, "type_id": 53, "participant_id": 20, "data": {"value": 4}, "location": "away"}, {"id": 691513322, "fixture_id": 18841694, "type_id": 55, "participant_id": 1, "data": {"value": 18}, "location": "home"}, {"id": 691513323, "fixture_id": 18841694, "type_id": 55, "participant_id": 20, "data": {"value": 11}, "location": "away"}, {"id": 24138175, "fixture_id": 18841694, "type_id": 56, "participant_id": 1, "data": {"value": 11}, "location": "home"}, {"id": 24138183, "fixture_id": 18841694, "type_id": 58, "participant_id": 20, "data": {"value": 1}, "location": "away"}, {"id": 24138574, "fixture_id": 18841694, "type_id": 78, "participant_id": 1, "data": {"value": 11}, "location": "home"}, {"id": 24138579, "fixture_id": 18841694, "type_id": 78, "participant_id": 20, "data": {"value": 8}, "location": "away"}, {"id": 24141187, "fixture_id": 18841694, "type_id": 54, "participant_id": 1, "data": {"value": 4}, "location": "home"}, {"id": 24141195, "fixture_id": 18841694, "type_id": 54, "participant_id": 20, "data": {"value": 10}, "location": "away"}, {"id": 24139926, "fixture_id": 18841694, "type_id": 117, "participant_id": 1, "data": {"value": 4}, "location": "home"}, {"id": 24139927, "fixture_id": 18841694, "type_id": 117, "participant_id": 20, "data": {"value": 8}, "location": "away"}, {"id": 24135288, "fixture_id": 18841694, "type_id": 42, "participant_id": 1, "data": {"value": 5}, "location": "home"}, {"id": 24135289, "fixture_id": 18841694, "type_id": 42, "participant_id": 20, "data": {"value": 10}, "location": "away"}, {"id": 24139797, "fixture_id": 18841694, "type_id": 99, "participant_id": 1, "data": {"value": 1}, "location": "home"}, {"id": 24138494, "fixture_id": 18841694, "type_id": 80, "participant_id": 20, "data": {"value": 603}, "location": "away"}, {"id": 24138484, "fixture_id": 18841694, "type_id": 80, "participant_id": 1, "data": {"value": 318}, "location": "home"}, {"id": 691513334, "fixture_id": 18841694, "type_id": 62, "participant_id": 1, "data": {"value": 61}, "location": "home"}, {"id": 691513335, "fixture_id": 18841694, "type_id": 62, "participant_id": 20, "data": {"value": 54}, "location": "away"}, {"id": 691513336, "fixture_id": 18841694, "type_id": 27264, "participant_id": 1, "data": {"value": 27}, "location": "home"}, {"id": 691513337, "fixture_id": 18841694, "type_id": 27264, "participant_id": 20, "data": {"value": 27}, "location": "away"}, {"id": 24139644, "fixture_id": 18841694, "type_id": 49, "participant_id": 1, "data": {"value": 3}, "location": "home"}, {"id": 24139649, "fixture_id": 18841694, "type_id": 49, "participant_id": 20, "data": {"value": 8}, "location": "away"}, {"id": 24141307, "fixture_id": 18841694, "type_id": 50, "participant_id": 1, "data": {"value": 2}, "location": "home"}, {"id": 24141306, "fixture_id": 18841694, "type_id": 50, "participant_id": 20, "data": {"value": 2}, "location": "away"}, {"id": 24140282, "fixture_id": 18841694, "type_id": 100, "participant_id": 1, "data": {"value": 8}, "location": "home"}, {"id": 24140284, "fixture_id": 18841694, "type_id": 100, "participant_id": 20, "data": {"value": 3}, "location": "away"}, {"id": 24139647, "fixture_id": 18841694, "type_id": 108, "participant_id": 1, "data": {"value": 9}, "location": "home"}, {"id": 24139650, "fixture_id": 18841694, "type_id": 108, "participant_id": 20, "data": {"value": 9}, "location": "away"}, {"id": 24139651, "fixture_id": 18841694, "type_id": 109, "participant_id": 20, "data": {"value": 6}, "location": "away"}, {"id": 24137207, "fixture_id": 18841694, "type_id": 82, "participant_id": 1, "data": {"value": 72}, "location": "home"}, {"id": 24137219, "fixture_id": 18841694, "type_id": 82, "participant_id": 20, "data": {"value": 86}, "location": "away"}, {"id": 691513338, "fixture_id": 18841694, "type_id": 27265, "participant_id": 1, "data": {"value": 44}, "location": "home"}, {"id": 691513339, "fixture_id": 18841694, "type_id": 27265, "participant_id": 20, "data": {"value": 50}, "location": "away"}, {"id": 24139648, "fixture_id": 18841694, "type_id": 1605, "participant_id": 1, "data": {"value": 67}, "location": "home"}, {"id": 24139652, "fixture_id": 18841694, "type_id": 1605, "participant_id": 20, "data": {"value": 67}, "location": "away"}, {"id": 24137572, "fixture_id": 18841694, "type_id": 45, "participant_id": 1, "data": {"value": 35}, "location": "home"}, {"id": 24137573, "fixture_id": 18841694, "type_id": 45, "participant_id": 20, "data": {"value": 65}, "location": "away"}, {"id": 24139708, "fixture_id": 18841694, "type_id": 98, "participant_id": 1, "data": {"value": 12}, "location": "home"}, {"id": 24139713, "fixture_id": 18841694, "type_id": 98, "participant_id": 20, "data": {"value": 10}, "location": "away"}, {"id": 691529004, "fixture_id": 18841694, "type_id": 1527, "participant_id": 1, "data": {"value": 2}, "location": "home"}, {"id": 691529005, "fixture_id": 18841694, "type_id": 1527, "participant_id": 20, "data": {"value": 3}, "location": "away"}], "state": {"id": 5, "state": "FT", "name": "Full Time", "short_name": "FT", "developer_name": "FT"}}, "subscription": [{"meta": {"trial_ends_at": "2026-02-01 08:22:54", "ends_at": "2026-02-18 07:24:30", "current_timestamp": 1768723026}, "plans": [{"plan": "European Plan", "sport": "Football", "category": "Advanced"}], "add_ons": [{"add_on": "European Club Tournaments", "sport": "Football", "category": "Plan"}], "widgets": []}], "rate_limit": {"resets_in_seconds": 2785, "remaining": 2348, "requested_entity": "Fixture"}, "timezone": "UTC"}}