{"_cached_at": "2026-01-18T13:16:08.679226", "data": {"data": [{"id": 3098, "sport_id": 1, "league_id": 8, "season_id": 12, "stage_id": 10, "group_id": null, "aggregate_id": null, "round_id": 304, "state_id": 5, "venue_id": 212, "name": "Sunderland vs Hull City", "starting_at": "2014-12-26 15:00:00", "result_info": "Hull City won after full-time.", "leg": "1/1", "details": null, "length": 90, "placeholder": false, "has_odds": false, "has_premium_odds": false, "starting_at_timestamp": 1419606000}, {"id": 3099, "sport_id": 1, "league_id": 8, "season_id": 3, "stage_id": 3, "group_id": null, "aggregate_id": null, "round_id": 305, "state_id": 5, "venue_id": 449, "name": "Newcastle United vs Everton", "starting_at": "2014-03-25 19:45:00", "result_info": "Everton won after full-time.", "leg": "1/1", "details": null, "length": 90, "placeholder": false, "has_odds": false, "has_premium_odds": false, "starting_at_timestamp": 1395776700}, {"id": 3100, "sport_id": 1, "league_id": 8, "season_id": 14, "stage_id": 12, "group_id": null, "aggregate_id": null, "round_id": 309, "state_id": 5, "venue_id": 449, "name": "Newcastle United vs West Ham United", "starting_at": "2007-09-23 12:30:00", "result_info": "Newcastle United won after full-time.", "leg": "1/1", "details": null, "length": 90, "placeholder": false, "has_odds": false, "has_premium_odds": false, "starting_at_timestamp": 1190550600}, {"id": 3101, "sport_id": 1, "league_id": 8, "season_id": 6, "stage_id": 4, "group_id": null, "aggregate_id": null, "round_id": 307, "state_id": 5, "venue_id": 203, "name": "Middlesbrough vs Aston Villa", "starting_at": "2009-05-16 14:00:00", "result_info": "Game ended in draw.", "leg": "1/1", "details": null, "length": 90, "placeholder": false, "has_odds": false, "has_premium_odds": false, "starting_at_timestamp": 1242482400}, {"id": 3102, "sport_id": 1, "league_id": 8, "season_id": 10, "stage_id": 8, "group_id": null, "aggregate_id": null, "round_id": 310, "state_id": 5, "venue_id": 321614, "name": "Chelsea vs Everton", "starting_at": "2016-01-16 15:00:00", "result_info": "Game ended in draw.", "leg": "1/1", "details": null, "length": 90, "placeholder": false, "has_odds": false, "has_premium_odds": false, "starting_at_timestamp": 1452956400}, {"id": 3104, "sport_id": 1, "league_id": 8, "season_id": 11, "stage_id": 9, "group_id": null, "aggregate_id": null, "round_id": 181, "state_id": 5, "venue_id": 492, "name": "Wolverhampton Wanderers vs Arsenal", "starting_at": "2009-11-07 17:30:00", "result_info": "Arsenal won after full-time.", "leg": "1/1", "details": null, "length": 90, "placeholder": false, "has_odds": false, "has_premium_odds": false, "starting_at_timestamp": 1257615000}, {"id": 3105, "sport_id": 1, "league_id": 8, "season_id": 7, "stage_id": 5, "group_id": null, "aggregate_id": null, "round_id": 308, "state_id": 5, "venue_id": 119, "name": "West Bromwich Albion vs Swansea City", "starting_at": "2013-03-09 15:00:00", "result_info": "West Bromwich Albion won after full-time.", "leg": "1/1", "details": null, "length": 90, "placeholder": false, "has_odds": false, "has_premium_odds": false, "starting_at_timestamp": 1362841200}, {"id": 3106, "sport_id": 1, "league_id": 8, "season_id": 13, "stage_id": 11, "group_id": null, "aggregate_id": null, "round_id": 302, "state_id": 5, "venue_id": 321614, "name": "Chelsea vs Manchester United", "starting_at": "2016-10-23 15:00:00", "result_info": "Chelsea won after full-time.", "leg": "1/1", "details": null, "length": 90, "placeholder": false, "has_odds": false, "has_premium_odds": false, "starting_at_timestamp": 1477234800}, {"id": 3107, "sport_id": 1, "league_id": 8, "season_id": 6, "stage_id": 4, "group_id": null, "aggregate_id": null, "round_id": 307, "state_id": 5, "venue_id": 12, "name": "Everton vs West Ham United", "starting_at": "2009-05-16 14:00:00", "result_info": "Everton won after full-time.", "leg": "1/1", "details": null, "length": 90, "placeholder": false, "has_odds": false, "has_premium_odds": false, "starting_at_timestamp": 1242482400}, {"id": 3108, "sport_id": 1, "league_id": 8, "season_id": 2, "stage_id": 2, "group_id": null, "aggregate_id": null, "round_id": 98, "state_id": 5, "venue_id": 10, "name": "Bolton Wanderers vs Liverpool", "starting_at": "2010-10-31 16:00:00", "result_info": "Liverpool won after full-time.", "leg": "1/1", "details": null, "length": 90, "placeholder": false, "has_odds": false, "has_premium_odds": false, "starting_at_timestamp": 1288540800}, {"id": 3109, "sport_id": 1, "league_id": 8, "season_id": 12, "stage_id": 10, "group_id": null, "aggregate_id": null, "round_id": 304, "state_id": 5, "venue_id": 208, "name": "Swansea City vs Aston Villa", "starting_at": "2014-12-26 15:00:00", "result_info": "Swansea City won after full-time.", "leg": "1/1", "details": null, "length": 90, "placeholder": false, "has_odds": false, "has_premium_odds": false, "starting_at_timestamp": 1419606000}, {"id": 3110, "sport_id": 1, "league_id": 8, "season_id": 14, "stage_id": 12, "group_id": null, "aggregate_id": null, "round_id": 309, "state_id": 5, "venue_id": 5, "name": "Aston Villa vs Everton", "starting_at": "2007-09-23 13:00:00", "result_info": "Aston Villa won after full-time.", "leg": "1/1", "details": null, "length": 90, "placeholder": false, "has_odds": false, "has_premium_odds": false, "starting_at_timestamp": 1190552400}, {"id": 3111, "sport_id": 1, "league_id": 8, "season_id": 3, "stage_id": 3, "group_id": null, "aggregate_id": null, "round_id": 305, "state_id": 5, "venue_id": 214, "name": "West Ham United vs Hull City", "starting_at": "2014-03-26 19:45:00", "result_info": "West Ham United won after full-time.", "leg": "1/1", "details": null, "length": 90, "placeholder": false, "has_odds": false, "has_premium_odds": false, "starting_at_timestamp": 1395863100}, {"id": 3112, "sport_id": 1, "league_id": 8, "season_id": 11, "stage_id": 9, "group_id": null, "aggregate_id": null, "round_id": 181, "state_id": 5, "venue_id": 199, "name": "Hull City vs Stoke City", "starting_at": "2009-11-08 13:30:00", "result_info": "Hull City won after full-time.", "leg": "1/1", "details": null, "length": 90, "placeholder": false, "has_odds": false, "has_premium_odds": false, "starting_at_timestamp": 1257687000}, {"id": 3114, "sport_id": 1, "league_id": 8, "season_id": 10, "stage_id": 8, "group_id": null, "aggregate_id": null, "round_id": 310, "state_id": 5, "venue_id": 146, "name": "AFC Bournemouth vs Norwich City", "starting_at": "2016-01-16 15:00:00", "result_info": "AFC Bournemouth won after full-time.", "leg": "1/1", "details": null, "length": 90, "placeholder": false, "has_odds": false, "has_premium_odds": false, "starting_at_timestamp": 1452956400}, {"id": 3115, "sport_id": 1, "league_id": 8, "season_id": 14, "stage_id": 12, "group_id": null, "aggregate_id": null, "round_id": 309, "state_id": 5, "venue_id": 383, "name": "Bolton Wanderers vs Tottenham Hotspur", "starting_at": "2007-09-23 14:00:00", "result_info": "Game ended in draw.", "leg": "1/1", "details": null, "length": 90, "placeholder": false, "has_odds": false, "has_premium_odds": false, "starting_at_timestamp": 1190556000}, {"id": 3116, "sport_id": 1, "league_id": 8, "season_id": 6, "stage_id": 4, "group_id": null, "aggregate_id": null, "round_id": 307, "state_id": 5, "venue_id": 383, "name": "Bolton Wanderers vs Hull City", "starting_at": "2009-05-16 14:00:00", "result_info": "Game ended in draw.", "leg": "1/1", "details": null, "length": 90, "placeholder": false, "has_odds": false, "has_premium_odds": false, "starting_at_timestamp": 1242482400}, {"id": 3117, "sport_id": 1, "league_id": 8, "season_id": 7, "stage_id": 5, "group_id": null, "aggregate_id": null, "round_id": 308, "state_id": 5, "venue_id": 449, "name": "Newcastle United vs Stoke City", "starting_at": "2013-03-10 15:00:00", "result_info": "Newcastle United won after full-time.", "leg": "1/1", "details": null, "length": 90, "placeholder": false, "has_odds": false, "has_premium_odds": false, "starting_at_timestamp": 1362927600}, {"id": 3118, "sport_id": 1, "league_id": 8, "season_id": 2, "stage_id": 2, "group_id": null, "aggregate_id": null, "round_id": 98, "state_id": 5, "venue_id": 339736, "name": "Blackpool vs West Bromwich Albion", "starting_at": "2010-11-01 20:00:00", "result_info": "Blackpool won after full-time.", "leg": "1/1", "details": null, "length": 90, "placeholder": false, "has_odds": false, "has_premium_odds": false, "starting_at_timestamp": 1288641600}, {"id": 3119, "sport_id": 1, "league_id": 8, "season_id": 13, "stage_id": 11, "group_id": null, "aggregate_id": null, "round_id": 312, "state_id": 5, "venue_id": 212, "name": "Sunderland vs Arsenal", "starting_at": "2016-10-29 11:30:00", "result_info": "Arsenal won after full-time.", "leg": "1/1", "details": null, "length": 90, "placeholder": false, "has_odds": false, "has_premium_odds": false, "starting_at_timestamp": 1477740600}, {"id": 3120, "sport_id": 1, "league_id": 8, "season_id": 12, "stage_id": 10, "group_id": null, "aggregate_id": null, "round_id": 304, "state_id": 5, "venue_id": 119, "name": "West Bromwich Albion vs Manchester City", "starting_at": "2014-12-26 15:00:00", "result_info": "Manchester City won after full-time.", "leg": "1/1", "details": null, "length": 90, "placeholder": false, "has_odds": false, "has_premium_odds": false, "starting_at_timestamp": 1419606000}, {"id": 3121, "sport_id": 1, "league_id": 8, "season_id": 3, "stage_id": 3, "group_id": null, "aggregate_id": null, "round_id": 305, "state_id": 5, "venue_id": 230, "name": "Liverpool vs Sunderland", "starting_at": "2014-03-26 20:00:00", "result_info": "Liverpool won after full-time.", "leg": "1/1", "details": null, "length": 90, "placeholder": false, "has_odds": false, "has_premium_odds": false, "starting_at_timestamp": 1395864000}, {"id": 3122, "sport_id": 1, "league_id": 8, "season_id": 11, "stage_id": 9, "group_id": null, "aggregate_id": null, "round_id": 181, "state_id": 5, "venue_id": 14, "name": "Wigan Athletic vs Fulham", "starting_at": "2009-11-08 15:00:00", "result_info": "Game ended in draw.", "leg": "1/1", "details": null, "length": 90, "placeholder": false, "has_odds": false, "has_premium_odds": false, "starting_at_timestamp": 1257692400}, {"id": 3123, "sport_id": 1, "league_id": 8, "season_id": 14, "stage_id": 12, "group_id": null, "aggregate_id": null, "round_id": 309, "state_id": 5, "venue_id": 339721, "name": "Blackburn Rovers vs Portsmouth", "starting_at": "2007-09-23 14:00:00", "result_info": "Portsmouth won after full-time.", "leg": "1/1", "details": null, "length": 90, "placeholder": false, "has_odds": false, "has_premium_odds": false, "starting_at_timestamp": 1190556000}, {"id": 3125, "sport_id": 1, "league_id": 8, "season_id": 6, "stage_id": 4, "group_id": null, "aggregate_id": null, "round_id": 307, "state_id": 5, "venue_id": 119, "name": "West Bromwich Albion vs Liverpool", "starting_at": "2009-05-17 12:30:00", "result_info": "Liverpool won after full-time.", "leg": "1/1", "details": null, "length": 90, "placeholder": false, "has_odds": false, "has_premium_odds": false, "starting_at_timestamp": 1242563400}], "pagination": {"count": 25, "per_page": 25, "current_page": 97, "next_page": "https://api.sportmonks.com/v3/football/fixtures?season_id=21646&page=98", "has_more": true}, "subscription": [{"meta": {"trial_ends_at": "2026-02-01 08:22:54", "ends_at": "2026-02-18 07:24:30", "current_timestamp": 1768722368}, "plans": [{"plan": "European Plan", "sport": "Football", "category": "Advanced"}], "add_ons": [{"add_on": "European Club Tournaments", "sport": "Football", "category": "Plan"}], "widgets": []}], "rate_limit": {"resets_in_seconds": 3443, "remaining": 2899, "requested_entity": "Fixture"}, "timezone": "UTC"}}