{"_cached_at": "2026-01-18T13:17:51.139614", "data": {"data": [{"id": 93810, "sport_id": 1, "league_id": 82, "season_id": 211, "stage_id": 495, "group_id": null, "aggregate_id": null, "round_id": 8587, "state_id": 5, "venue_id": 2769, "name": "Karlsruher SC vs Wolfsburg", "starting_at": "2008-09-28 15:00:00", "result_info": "Karlsruher SC won after full-time.", "leg": "1/1", "details": null, "length": 90, "placeholder": false, "has_odds": false, "has_premium_odds": false, "starting_at_timestamp": 1222614000}, {"id": 93811, "sport_id": 1, "league_id": 82, "season_id": 212, "stage_id": 496, "group_id": null, "aggregate_id": null, "round_id": 8784, "state_id": 5, "venue_id": 2138, "name": "Schalke 04 vs Bayern M\u00fcnchen", "starting_at": "2010-04-03 13:30:00", "result_info": "FC Bayern M\u00fcnchen won after full-time.", "leg": "1/1", "details": null, "length": 90, "placeholder": false, "has_odds": false, "has_premium_odds": false, "starting_at_timestamp": 1270301400}, {"id": 93813, "sport_id": 1, "league_id": 82, "season_id": 214, "stage_id": 498, "group_id": null, "aggregate_id": null, "round_id": 8592, "state_id": 5, "venue_id": 180, "name": "Borussia M'gladbach vs Wolfsburg", "starting_at": "2011-08-19 18:30:00", "result_info": "Borussia M\u00f6nchengladbach won after full-time.", "leg": "1/1", "details": null, "length": 90, "placeholder": false, "has_odds": false, "has_premium_odds": false, "starting_at_timestamp": 1313778600}, {"id": 93815, "sport_id": 1, "league_id": 82, "season_id": 213, "stage_id": 497, "group_id": null, "aggregate_id": null, "round_id": 8588, "state_id": 5, "venue_id": 1945, "name": "Stuttgart vs Borussia M'gladbach", "starting_at": "2010-09-18 13:30:00", "result_info": "VfB Stuttgart won after full-time.", "leg": "1/1", "details": null, "length": 90, "placeholder": false, "has_odds": false, "has_premium_odds": false, "starting_at_timestamp": 1284816600}, {"id": 93818, "sport_id": 1, "league_id": 82, "season_id": 211, "stage_id": 495, "group_id": null, "aggregate_id": null, "round_id": 8587, "state_id": 5, "venue_id": 2169, "name": "Eintracht Frankfurt vs Arminia Bielefeld", "starting_at": "2008-09-28 15:00:00", "result_info": "Game ended in draw.", "leg": "1/1", "details": null, "length": 90, "placeholder": false, "has_odds": false, "has_premium_odds": false, "starting_at_timestamp": 1222614000}, {"id": 93820, "sport_id": 1, "league_id": 82, "season_id": 212, "stage_id": 496, "group_id": null, "aggregate_id": null, "round_id": 8784, "state_id": 5, "venue_id": 1946, "name": "K\u00f6ln vs Hertha BSC", "starting_at": "2010-04-03 16:30:00", "result_info": "Hertha BSC won after full-time.", "leg": "1/1", "details": null, "length": 90, "placeholder": false, "has_odds": false, "has_premium_odds": false, "starting_at_timestamp": 1270312200}, {"id": 93823, "sport_id": 1, "league_id": 82, "season_id": 214, "stage_id": 498, "group_id": null, "aggregate_id": null, "round_id": 8592, "state_id": 5, "venue_id": 2166, "name": "Borussia Dortmund vs N\u00fcrnberg", "starting_at": "2011-08-20 13:30:00", "result_info": "Borussia Dortmund won after full-time.", "leg": "1/1", "details": null, "length": 90, "placeholder": false, "has_odds": false, "has_premium_odds": false, "starting_at_timestamp": 1313847000}, {"id": 93825, "sport_id": 1, "league_id": 82, "season_id": 213, "stage_id": 497, "group_id": null, "aggregate_id": null, "round_id": 8588, "state_id": 5, "venue_id": 80, "name": "Wolfsburg vs Hannover 96", "starting_at": "2010-09-18 13:30:00", "result_info": "VfL Wolfsburg won after full-time.", "leg": "1/1", "details": null, "length": 90, "placeholder": false, "has_odds": false, "has_premium_odds": false, "starting_at_timestamp": 1284816600}, {"id": 93826, "sport_id": 1, "league_id": 82, "season_id": 211, "stage_id": 495, "group_id": null, "aggregate_id": null, "round_id": 8596, "state_id": 5, "venue_id": 1719, "name": "Arminia Bielefeld vs Karlsruher SC", "starting_at": "2008-10-03 18:30:00", "result_info": "Karlsruher SC won after full-time.", "leg": "1/1", "details": null, "length": 90, "placeholder": false, "has_odds": false, "has_premium_odds": false, "starting_at_timestamp": 1223058600}, {"id": 93827, "sport_id": 1, "league_id": 82, "season_id": 212, "stage_id": 496, "group_id": null, "aggregate_id": null, "round_id": 8784, "state_id": 5, "venue_id": 80, "name": "Wolfsburg vs Hoffenheim", "starting_at": "2010-04-04 13:30:00", "result_info": "VfL Wolfsburg won after full-time.", "leg": "1/1", "details": null, "length": 90, "placeholder": false, "has_odds": false, "has_premium_odds": false, "starting_at_timestamp": 1270387800}, {"id": 93832, "sport_id": 1, "league_id": 82, "season_id": 214, "stage_id": 498, "group_id": null, "aggregate_id": null, "round_id": 8592, "state_id": 5, "venue_id": 53, "name": "Bayern M\u00fcnchen vs Hamburger SV", "starting_at": "2011-08-20 13:30:00", "result_info": "FC Bayern M\u00fcnchen won after full-time.", "leg": "1/1", "details": null, "length": 90, "placeholder": false, "has_odds": false, "has_premium_odds": false, "starting_at_timestamp": 1313847000}, {"id": 93834, "sport_id": 1, "league_id": 82, "season_id": 211, "stage_id": 495, "group_id": null, "aggregate_id": null, "round_id": 8596, "state_id": 5, "venue_id": 1978, "name": "Hoffenheim vs Eintracht Frankfurt", "starting_at": "2008-10-04 13:30:00", "result_info": "TSG Hoffenheim won after full-time.", "leg": "1/1", "details": null, "length": 90, "placeholder": false, "has_odds": false, "has_premium_odds": false, "starting_at_timestamp": 1223127000}, {"id": 93835, "sport_id": 1, "league_id": 82, "season_id": 213, "stage_id": 497, "group_id": null, "aggregate_id": null, "round_id": 8588, "state_id": 5, "venue_id": 798, "name": "Kaiserslautern vs Hoffenheim", "starting_at": "2010-09-18 13:30:00", "result_info": "Game ended in draw.", "leg": "1/1", "details": null, "length": 90, "placeholder": false, "has_odds": false, "has_premium_odds": false, "starting_at_timestamp": 1284816600}, {"id": 93836, "sport_id": 1, "league_id": 82, "season_id": 212, "stage_id": 496, "group_id": null, "aggregate_id": null, "round_id": 8784, "state_id": 5, "venue_id": 2076, "name": "Hamburger SV vs Hannover 96", "starting_at": "2010-04-04 15:30:00", "result_info": "Game ended in draw.", "leg": "1/1", "details": null, "length": 90, "placeholder": false, "has_odds": false, "has_premium_odds": false, "starting_at_timestamp": 1270395000}, {"id": 93840, "sport_id": 1, "league_id": 82, "season_id": 214, "stage_id": 498, "group_id": null, "aggregate_id": null, "round_id": 8592, "state_id": 5, "venue_id": 2172, "name": "Werder Bremen vs Freiburg", "starting_at": "2011-08-20 13:30:00", "result_info": "Werder Bremen won after full-time.", "leg": "1/1", "details": null, "length": 90, "placeholder": false, "has_odds": false, "has_premium_odds": false, "starting_at_timestamp": 1313847000}, {"id": 93843, "sport_id": 1, "league_id": 82, "season_id": 211, "stage_id": 495, "group_id": null, "aggregate_id": null, "round_id": 8596, "state_id": 5, "venue_id": 180, "name": "Borussia M'gladbach vs K\u00f6ln", "starting_at": "2008-10-04 13:30:00", "result_info": "FC K\u00f6ln won after full-time.", "leg": "1/1", "details": null, "length": 90, "placeholder": false, "has_odds": false, "has_premium_odds": false, "starting_at_timestamp": 1223127000}, {"id": 93844, "sport_id": 1, "league_id": 82, "season_id": 212, "stage_id": 496, "group_id": null, "aggregate_id": null, "round_id": 8793, "state_id": 5, "venue_id": 180, "name": "Borussia M'gladbach vs Eintracht Frankfurt", "starting_at": "2010-04-09 18:30:00", "result_info": "Borussia M\u00f6nchengladbach won after full-time.", "leg": "1/1", "details": null, "length": 90, "placeholder": false, "has_odds": false, "has_premium_odds": false, "starting_at_timestamp": 1270837800}, {"id": 93845, "sport_id": 1, "league_id": 82, "season_id": 213, "stage_id": 497, "group_id": null, "aggregate_id": null, "round_id": 8588, "state_id": 5, "venue_id": 2110, "name": "St. Pauli vs Hamburger SV", "starting_at": "2010-09-19 13:30:00", "result_info": "Game ended in draw.", "leg": "1/1", "details": null, "length": 90, "placeholder": false, "has_odds": false, "has_premium_odds": false, "starting_at_timestamp": 1284903000}, {"id": 93848, "sport_id": 1, "league_id": 82, "season_id": 211, "stage_id": 495, "group_id": null, "aggregate_id": null, "round_id": 8596, "state_id": 5, "venue_id": 1947, "name": "Bayer Leverkusen vs Hertha BSC", "starting_at": "2008-10-04 13:30:00", "result_info": "Hertha BSC won after full-time.", "leg": "1/1", "details": null, "length": 90, "placeholder": false, "has_odds": false, "has_premium_odds": false, "starting_at_timestamp": 1223127000}, {"id": 93850, "sport_id": 1, "league_id": 82, "season_id": 212, "stage_id": 496, "group_id": null, "aggregate_id": null, "round_id": 8793, "state_id": 5, "venue_id": 2172, "name": "Werder Bremen vs Freiburg", "starting_at": "2010-04-10 13:30:00", "result_info": "Werder Bremen won after full-time.", "leg": "1/1", "details": null, "length": 90, "placeholder": false, "has_odds": false, "has_premium_odds": false, "starting_at_timestamp": 1270906200}, {"id": 93853, "sport_id": 1, "league_id": 82, "season_id": 214, "stage_id": 498, "group_id": null, "aggregate_id": null, "round_id": 8592, "state_id": 5, "venue_id": 1945, "name": "Stuttgart vs Bayer Leverkusen", "starting_at": "2011-08-20 13:30:00", "result_info": "Bayer 04 Leverkusen won after full-time.", "leg": "1/1", "details": null, "length": 90, "placeholder": false, "has_odds": false, "has_premium_odds": false, "starting_at_timestamp": 1313847000}, {"id": 93854, "sport_id": 1, "league_id": 82, "season_id": 213, "stage_id": 497, "group_id": null, "aggregate_id": null, "round_id": 8588, "state_id": 5, "venue_id": 2138, "name": "Schalke 04 vs Borussia Dortmund", "starting_at": "2010-09-19 15:30:00", "result_info": "Borussia Dortmund won after full-time.", "leg": "1/1", "details": null, "length": 90, "placeholder": false, "has_odds": false, "has_premium_odds": false, "starting_at_timestamp": 1284910200}, {"id": 93856, "sport_id": 1, "league_id": 82, "season_id": 211, "stage_id": 495, "group_id": null, "aggregate_id": null, "round_id": 8596, "state_id": 5, "venue_id": 1945, "name": "Stuttgart vs Werder Bremen", "starting_at": "2008-10-04 13:30:00", "result_info": "VfB Stuttgart won after full-time.", "leg": "1/1", "details": null, "length": 90, "placeholder": false, "has_odds": false, "has_premium_odds": false, "starting_at_timestamp": 1223127000}, {"id": 93858, "sport_id": 1, "league_id": 82, "season_id": 212, "stage_id": 496, "group_id": null, "aggregate_id": null, "round_id": 8793, "state_id": 5, "venue_id": 1618, "name": "Hoffenheim vs K\u00f6ln", "starting_at": "2010-04-10 13:30:00", "result_info": "FC K\u00f6ln won after full-time.", "leg": "1/1", "details": null, "length": 90, "placeholder": false, "has_odds": false, "has_premium_odds": false, "starting_at_timestamp": 1270906200}, {"id": 93861, "sport_id": 1, "league_id": 82, "season_id": 214, "stage_id": 498, "group_id": null, "aggregate_id": null, "round_id": 8592, "state_id": 5, "venue_id": 2096, "name": "Augsburg vs Hoffenheim", "starting_at": "2011-08-20 13:30:00", "result_info": "TSG Hoffenheim won after full-time.", "leg": "1/1", "details": null, "length": 90, "placeholder": false, "has_odds": false, "has_premium_odds": false, "starting_at_timestamp": 1313847000}], "pagination": {"count": 25, "per_page": 25, "current_page": 302, "next_page": "https://api.sportmonks.com/v3/football/fixtures?season_id=21646&page=303", "has_more": true}, "subscription": [{"meta": {"trial_ends_at": "2026-02-01 08:22:54", "ends_at": "2026-02-18 07:24:30", "current_timestamp": 1768722470}, "plans": [{"plan": "European Plan", "sport": "Football", "category": "Advanced"}], "add_ons": [{"add_on": "European Club Tournaments", "sport": "Football", "category": "Plan"}], "widgets": []}], "rate_limit": {"resets_in_seconds": 3341, "remaining": 2694, "requested_entity": "Fixture"}, "timezone": "UTC"}}